fairscape_cli/__init__.py
fairscape_cli/__main__.py
fairscape_cli/config.py
fairscape_cli/commands/__init__.py
fairscape_cli/commands/augment_commands.py
fairscape_cli/commands/build_commands.py
fairscape_cli/commands/import_commands.py
fairscape_cli/commands/publish_commands.py
fairscape_cli/commands/rocrate_commands.py
fairscape_cli/commands/schema_commands.py
fairscape_cli/commands/track.py
fairscape_cli/data_fetcher/GenomicData.py
fairscape_cli/data_fetcher/PhysioNetImporter.py
fairscape_cli/data_fetcher/__init__.py
fairscape_cli/data_fetcher/bioproject_fetcher.py
fairscape_cli/data_fetcher/cell_line_api.py
fairscape_cli/data_fetcher/generic_data/__init__.py
fairscape_cli/data_fetcher/generic_data/research_data.py
fairscape_cli/data_fetcher/generic_data/connectors/__init__.py
fairscape_cli/data_fetcher/generic_data/connectors/dataverse_connector.py
fairscape_cli/data_fetcher/generic_data/connectors/figshare_connector.py
fairscape_cli/datasheet_builder/__init__.py
fairscape_cli/datasheet_builder/generate_datasheet.py
fairscape_cli/datasheet_builder/evidence_graph/__init__.py
fairscape_cli/datasheet_builder/evidence_graph/graph_builder.py
fairscape_cli/datasheet_builder/evidence_graph/html_builder.py
fairscape_cli/datasheet_builder/rocrate/__init__.py
fairscape_cli/datasheet_builder/rocrate/datasheet_generator.py
fairscape_cli/datasheet_builder/rocrate/section_generators.py
fairscape_cli/datasheet_builder/rocrate/utilities/__init__.py
fairscape_cli/datasheet_builder/templates/base.html
fairscape_cli/datasheet_builder/templates/preview.html
fairscape_cli/datasheet_builder/templates/sections/distribution.html
fairscape_cli/datasheet_builder/templates/sections/overview.html
fairscape_cli/datasheet_builder/templates/sections/subcrates.html
fairscape_cli/datasheet_builder/templates/sections/use_cases.html
fairscape_cli/entailments/__init__.py
fairscape_cli/entailments/evi.xml
fairscape_cli/entailments/find_outputs.py
fairscape_cli/entailments/inverse.py
fairscape_cli-1.1.10.dist-info/licenses/LICENSE
fairscape_cli-1.1.10.dist-info/METADATA
fairscape_cli-1.1.10.dist-info/WHEEL
fairscape_cli-1.1.10.dist-info/entry_points.txt
fairscape_cli-1.1.10.dist-info/top_level.txt
fairscape_cli-1.1.10.dist-info/RECORD
