Metadata-Version: 2.4
Name: fairscape-cli
Version: 1.1.10
Summary: A utility for packaging objects and validating metadata for FAIRSCAPE
Author-email: Max Levinson <mal8ch@virginia.edu>, Justin Niestroy <jniestroy@gmail.com>, Sadnan Al Manir <sadnanalmanir@gmail.com>, Tim Clark <twc8q@virginia.edu>
License: Copyright 2023 THE RECTOR AND VISITORS OF THE UNIVERSITY OF VIRGINIA
Project-URL: Homepage, https://github.com/fairscape/fairscape-cli
Project-URL: Documentation, https://fairscape.github.io/fairscape-cli/
Project-URL: Repository, https://github.com/fairscape/fairscape-cli.git
Project-URL: Issues, https://github.com/fairscape/fairscape-cli/issues
Project-URL: Changelog, https://github.com/fairscape/fairscape-cli/blob/main/CHANGELOG.md
Project-URL: Citation, https://github.com/fairscape/fairscape-cli/blob/main/CITATION.cff
Keywords: fairscape,reproducibility,FAIR,B2AI,CLI,RO-Crate
Classifier: Development Status :: 5 - Production/Stable
Classifier: Intended Audience :: Developers
Classifier: Intended Audience :: Science/Research
Classifier: Topic :: Software Development :: Build Tools
Classifier: Environment :: Console
Classifier: Framework :: Pydantic :: 2
Classifier: Programming Language :: Python
Classifier: Programming Language :: Python :: 3.8
Classifier: Programming Language :: Python :: 3.9
Classifier: Programming Language :: Python :: 3.10
Classifier: Programming Language :: Python :: 3.11
Classifier: Operating System :: OS Independent
Classifier: Topic :: File Formats :: JSON
Classifier: Topic :: Scientific/Engineering :: Bio-Informatics
Classifier: Topic :: Software Development :: Libraries :: Python Modules
Requires-Python: >=3.8
License-File: LICENSE
Requires-Dist: click>=8.1.7
Requires-Dist: pydantic>=2.5.1
Requires-Dist: prettytable>=3.9.0
Requires-Dist: jsonschema>=4.20.0
Requires-Dist: sqids>=0.4.1
Requires-Dist: fairscape-models>=1.0.21
Requires-Dist: pyyaml
Requires-Dist: h5py
Requires-Dist: frictionless<6.0,>=5.0
Requires-Dist: beautifulsoup4
Requires-Dist: pandas
Requires-Dist: rdflib
Requires-Dist: mongomock
Requires-Dist: huggingface_hub>=0.20.0
Provides-Extra: test
Requires-Dist: pytest; extra == "test"
Requires-Dist: pytest-cov; extra == "test"
Dynamic: license-file
